odoo/addons/pos_fix_search_limit/README.rst
odoo/addons/pos_fix_search_limit/__init__.py
odoo/addons/pos_fix_search_limit/__manifest__.py
odoo/addons/pos_fix_search_limit/i18n/ca.po
odoo/addons/pos_fix_search_limit/i18n/es.po
odoo/addons/pos_fix_search_limit/i18n/pos_fix_search_limit.pot
odoo/addons/pos_fix_search_limit/static/description/icon.png
odoo/addons/pos_fix_search_limit/static/src/js/pos_fix_search_limit.js
odoo/addons/pos_fix_search_limit/views/pos_fix_limit.xml
odoo11_addon_pos_fix_search_limit-11.0.1.0.1.dist-info/METADATA
odoo11_addon_pos_fix_search_limit-11.0.1.0.1.dist-info/WHEEL
odoo11_addon_pos_fix_search_limit-11.0.1.0.1.dist-info/top_level.txt
odoo11_addon_pos_fix_search_limit-11.0.1.0.1.dist-info/RECORD
